grab_bin_dist/__init__.py
grab_bin_dist/defs.py
grab_bin_dist/fetch.py
grab_bin_dist/py.typed
grab_bin_dist/rdocker.py
grab_bin_dist/text.py
grab_bin_dist/util.py
grab_bin_dist/worker.py
grab_bin_dist/sample/__init__.py
grab_bin_dist/sample/pack_uv.py
grab_bin_dist-0.1.0.dist-info/METADATA
grab_bin_dist-0.1.0.dist-info/WHEEL
grab_bin_dist-0.1.0.dist-info/entry_points.txt
grab_bin_dist-0.1.0.dist-info/licenses/LICENSES/BSD-2-Clause.txt
grab_bin_dist-0.1.0.dist-info/RECORD
